[
  {
    "ContainingType": "Movies.api.Controllers.GenresController",
    "Method": "GetAllAsync",
    "RelativePath": "api/Genres",
    "HttpMethod": "GET",
    "IsController": true,
    "Order": 0,
    "Parameters": [],
    "ReturnTypes": []
  },
  {
    "ContainingType": "Movies.api.Controllers.GenresController",
    "Method": "CreateAsync",
    "RelativePath": "api/Genres",
    "HttpMethod": "POST",
    "IsController": true,
    "Order": 0,
    "Parameters": [
      {
        "Name": "genreDto",
        "Type": "Movies.api.Dtos.GenreDto",
        "IsRequired": true
      }
    ],
    "ReturnTypes": []
  },
  {
    "ContainingType": "Movies.api.Controllers.GenresController",
    "Method": "UpdateAsync",
    "RelativePath": "api/Genres/{id}",
    "HttpMethod": "PUT",
    "IsController": true,
    "Order": 0,
    "Parameters": [
      {
        "Name": "id",
        "Type": "System.Byte",
        "IsRequired": true
      },
      {
        "Name": "genreDto",
        "Type": "Movies.api.Dtos.GenreDto",
        "IsRequired": true
      }
    ],
    "ReturnTypes": []
  },
  {
    "ContainingType": "Movies.api.Controllers.GenresController",
    "Method": "DeleteAsync",
    "RelativePath": "api/Genres/{id}",
    "HttpMethod": "DELETE",
    "IsController": true,
    "Order": 0,
    "Parameters": [
      {
        "Name": "id",
        "Type": "System.Byte",
        "IsRequired": true
      }
    ],
    "ReturnTypes": []
  },
  {
    "ContainingType": "Movies.api.Controllers.MoviesController",
    "Method": "GetAllAsync",
    "RelativePath": "api/Movies",
    "HttpMethod": "GET",
    "IsController": true,
    "Order": 0,
    "Parameters": [],
    "ReturnTypes": []
  },
  {
    "ContainingType": "Movies.api.Controllers.MoviesController",
    "Method": "CreateAsync",
    "RelativePath": "api/Movies",
    "HttpMethod": "POST",
    "IsController": true,
    "Order": 0,
    "Parameters": [
      {
        "Name": "Title",
        "Type": "System.String",
        "IsRequired": false
      },
      {
        "Name": "Year",
        "Type": "System.Int32",
        "IsRequired": false
      },
      {
        "Name": "Rate",
        "Type": "System.Double",
        "IsRequired": false
      },
      {
        "Name": "StoryLine",
        "Type": "System.String",
        "IsRequired": false
      },
      {
        "Name": "Poster",
        "Type": "Microsoft.AspNetCore.Http.IFormFile",
        "IsRequired": false
      },
      {
        "Name": "GenreId",
        "Type": "System.Byte",
        "IsRequired": false
      }
    ],
    "ReturnTypes": []
  },
  {
    "ContainingType": "Movies.api.Controllers.MoviesController",
    "Method": "GetByIdAsync",
    "RelativePath": "api/Movies/{id}",
    "HttpMethod": "GET",
    "IsController": true,
    "Order": 0,
    "Parameters": [
      {
        "Name": "id",
        "Type": "System.Int32",
        "IsRequired": true
      }
    ],
    "ReturnTypes": []
  },
  {
    "ContainingType": "Movies.api.Controllers.MoviesController",
    "Method": "UpdateAsync",
    "RelativePath": "api/Movies/{id}",
    "HttpMethod": "PUT",
    "IsController": true,
    "Order": 0,
    "Parameters": [
      {
        "Name": "id",
        "Type": "System.Int32",
        "IsRequired": true
      },
      {
        "Name": "Title",
        "Type": "System.String",
        "IsRequired": false
      },
      {
        "Name": "Year",
        "Type": "System.Int32",
        "IsRequired": false
      },
      {
        "Name": "Rate",
        "Type": "System.Double",
        "IsRequired": false
      },
      {
        "Name": "StoryLine",
        "Type": "System.String",
        "IsRequired": false
      },
      {
        "Name": "Poster",
        "Type": "Microsoft.AspNetCore.Http.IFormFile",
        "IsRequired": false
      },
      {
        "Name": "GenreId",
        "Type": "System.Byte",
        "IsRequired": false
      }
    ],
    "ReturnTypes": []
  },
  {
    "ContainingType": "Movies.api.Controllers.MoviesController",
    "Method": "DeleteAsync",
    "RelativePath": "api/Movies/{id}",
    "HttpMethod": "DELETE",
    "IsController": true,
    "Order": 0,
    "Parameters": [
      {
        "Name": "id",
        "Type": "System.Int32",
        "IsRequired": true
      }
    ],
    "ReturnTypes": []
  },
  {
    "ContainingType": "Movies.api.Controllers.MoviesController",
    "Method": "GetByGenreIdAsync",
    "RelativePath": "api/Movies/GetByGenreId",
    "HttpMethod": "GET",
    "IsController": true,
    "Order": 0,
    "Parameters": [
      {
        "Name": "genreId",
        "Type": "System.Byte",
        "IsRequired": false
      }
    ],
    "ReturnTypes": []
  }
]